<?xml version="1.0" encoding="utf-8"?><sketch label="mu"><stroke><point x="150.592" y="185.088" time="0" /><point x="151.592" y="185.088" time="156458" /><point x="153.592" y="184.088" time="156458" /><point x="158.592" y="183.088" time="313251" /><point x="163.592" y="182.088" time="313251" /><point x="169.592" y="181.088" time="469322" /><point x="176.592" y="180.088" time="469322" /><point x="183.592" y="178.088" time="625201" /><point x="192.592" y="177.088" time="625201" /><point x="201.592" y="175.088" time="781903" /><point x="233.592" y="171.088" time="938252" /><point x="255.592" y="168.088" time="1094067" /><point x="274.592" y="166.088" time="1250003" /><point x="291.592" y="165.088" time="1407019" /><point x="303.592" y="166.088" time="1563263" /><point x="310.592" y="166.088" time="1719386" /><point x="310.592" y="166.088" time="1875750" /></stroke><stroke><point x="223.592" y="104.088" time="0" /><point x="221.592" y="102.088" time="156554" /><point x="221.592" y="102.088" time="312958" /><point x="221.592" y="103.088" time="312958" /><point x="221.592" y="105.088" time="468758" /><point x="221.592" y="108.088" time="468758" /><point x="222.592" y="111.088" time="624678" /><point x="223.592" y="116.088" time="624678" /><point x="225.592" y="121.088" time="781815" /><point x="227.592" y="126.088" time="781815" /><point x="229.592" y="133.088" time="781815" /><point x="231.592" y="140.088" time="938035" /><point x="235.592" y="158.088" time="1093660" /><point x="239.592" y="179.088" time="1250531" /><point x="242.592" y="200.088" time="1406814" /><point x="243.592" y="220.088" time="1563018" /><point x="244.592" y="246.088" time="1718782" /><point x="242.592" y="262.088" time="1874760" /><point x="241.592" y="269.088" time="1874760" /><point x="239.592" y="275.088" time="2031269" /><point x="235.592" y="285.088" time="2187507" /><point x="229.592" y="293.088" time="2344112" /><point x="221.592" y="299.088" time="2543993" /><point x="207.592" y="305.088" time="2701018" /><point x="198.592" y="305.088" time="2857265" /><point x="188.592" y="304.088" time="3013484" /><point x="175.592" y="297.088" time="3169791" /><point x="169.592" y="291.088" time="3325881" /><point x="167.592" y="284.088" time="3482330" /><point x="169.592" y="275.088" time="3638579" /><point x="175.592" y="266.088" time="3794503" /><point x="184.592" y="256.088" time="3950524" /><point x="194.592" y="250.088" time="4106580" /><point x="203.592" y="246.088" time="4263026" /><point x="213.592" y="248.088" time="4419761" /><point x="218.592" y="252.088" time="4575775" /><point x="222.592" y="258.088" time="4732330" /><point x="224.592" y="265.088" time="4888549" /><point x="225.592" y="279.088" time="5044455" /><point x="224.592" y="290.088" time="5201049" /><point x="222.592" y="302.088" time="5356788" /><point x="219.592" y="316.088" time="5513593" /><point x="216.592" y="331.088" time="5669825" /><point x="214.592" y="346.088" time="5825878" /><point x="214.592" y="359.088" time="5981778" /><point x="214.592" y="364.088" time="5981778" /><point x="216.592" y="369.088" time="6138036" /><point x="224.592" y="382.088" time="6294500" /><point x="232.592" y="389.088" time="6451091" /><point x="244.592" y="395.088" time="6607325" /><point x="257.592" y="401.088" time="6763026" /><point x="273.592" y="406.088" time="6919840" /><point x="299.592" y="410.088" time="7231790" /><point x="317.592" y="410.088" time="7387822" /><point x="351.592" y="405.088" time="7544509" /><point x="364.592" y="400.088" time="7701085" /><point x="374.592" y="394.088" time="7856779" /><point x="381.592" y="388.088" time="8013071" /><point x="384.592" y="381.088" time="8169284" /><point x="385.592" y="371.088" time="8325893" /><point x="383.592" y="366.088" time="8481796" /><point x="381.592" y="361.088" time="8638519" /><point x="381.592" y="357.088" time="8794443" /><point x="381.592" y="353.088" time="8951018" /><point x="381.592" y="349.088" time="9154952" /><point x="381.592" y="349.088" time="9154952" /></stroke><stroke><point x="368.592" y="108.088" time="0" /><point x="369.592" y="108.088" time="156802" /><point x="371.592" y="110.088" time="156802" /><point x="375.592" y="112.088" time="312288" /><point x="379.592" y="114.088" time="312288" /><point x="384.592" y="117.088" time="468749" /><point x="389.592" y="121.088" time="468749" /><point x="394.592" y="124.088" time="624821" /><point x="398.592" y="128.088" time="624821" /><point x="404.592" y="135.088" time="781251" /><point x="406.592" y="139.088" time="937492" /><point x="408.592" y="149.088" time="1094107" /><point x="408.592" y="149.088" time="1250522" /></stroke></sketch>