<?xml version="1.0" encoding="utf-8"?><sketch label="ne"><stroke><point x="154.264" y="88.032" time="0" /><point x="153.264" y="88.032" time="117250" /><point x="153.264" y="88.032" time="127313" /><point x="153.264" y="87.032" time="317381" /><point x="153.264" y="87.032" time="327432" /><point x="153.264" y="87.032" time="477025" /><point x="153.264" y="87.032" time="486814" /><point x="153.264" y="87.032" time="756650" /><point x="154.264" y="88.032" time="766837" /><point x="154.264" y="88.032" time="877089" /><point x="154.264" y="89.032" time="886510" /><point x="154.264" y="91.032" time="1056832" /><point x="154.264" y="92.032" time="1056832" /><point x="154.264" y="94.032" time="1237115" /><point x="154.264" y="101.032" time="1478341" /><point x="154.264" y="105.032" time="1598336" /><point x="154.264" y="109.032" time="1758355" /><point x="155.264" y="114.032" time="1878360" /><point x="155.264" y="121.032" time="2118375" /><point x="156.264" y="131.032" time="2398386" /><point x="156.264" y="136.032" time="2518388" /><point x="156.264" y="141.032" time="2628411" /><point x="156.264" y="146.032" time="2768418" /><point x="156.264" y="153.032" time="3038423" /><point x="155.264" y="157.032" time="3158434" /><point x="155.264" y="163.032" time="3288432" /><point x="154.264" y="168.032" time="3398449" /><point x="154.264" y="171.032" time="3478449" /><point x="153.264" y="178.032" time="3678457" /><point x="153.264" y="184.032" time="3838467" /><point x="151.264" y="196.032" time="4118490" /><point x="150.264" y="201.032" time="4188511" /><point x="150.264" y="206.032" time="4398501" /><point x="150.264" y="211.032" time="4508973" /><point x="150.264" y="219.032" time="4758527" /><point x="150.264" y="224.032" time="4878535" /><point x="150.264" y="229.032" time="4999034" /><point x="149.264" y="234.032" time="5158540" /><point x="149.264" y="242.032" time="5397028" /><point x="149.264" y="248.032" time="5517488" /><point x="148.264" y="253.032" time="5679034" /><point x="148.264" y="259.032" time="5799032" /><point x="148.264" y="264.032" time="5911901" /><point x="148.264" y="269.032" time="6050674" /><point x="148.264" y="277.032" time="6324822" /><point x="148.264" y="283.032" time="6444830" /><point x="148.264" y="288.032" time="6604332" /><point x="148.264" y="294.032" time="6724216" /><point x="148.264" y="301.032" time="6904339" /><point x="148.264" y="304.032" time="6914146" /><point x="148.264" y="306.032" time="7124162" /><point x="148.264" y="312.032" time="7245051" /><point x="148.264" y="319.032" time="7395857" /><point x="149.264" y="326.032" time="7527974" /><point x="149.264" y="334.032" time="7679450" /><point x="150.264" y="342.032" time="7799533" /><point x="150.264" y="352.032" time="8041100" /><point x="150.264" y="359.032" time="8157728" /><point x="150.264" y="365.032" time="8268397" /><point x="150.264" y="372.032" time="8437742" /><point x="150.264" y="380.032" time="8677769" /><point x="150.264" y="385.032" time="8797777" /><point x="150.264" y="388.032" time="8957786" /><point x="150.264" y="391.032" time="9077791" /><point x="150.264" y="393.032" time="9188357" /><point x="150.264" y="394.032" time="9327975" /><point x="150.264" y="396.032" time="9597682" /><point x="151.264" y="397.032" time="9788468" /><point x="151.264" y="398.032" time="9940267" /><point x="151.264" y="398.032" time="9969744" /></stroke><stroke><point x="79.264" y="176.032" time="0" /><point x="78.264" y="176.032" time="99335" /><point x="78.264" y="176.032" time="129392" /><point x="77.264" y="177.032" time="302668" /><point x="76.264" y="177.032" time="322876" /><point x="76.264" y="178.032" time="459428" /><point x="76.264" y="178.032" time="609495" /><point x="76.264" y="178.032" time="609495" /><point x="76.264" y="179.032" time="759517" /><point x="77.264" y="179.032" time="779498" /><point x="77.264" y="179.032" time="859498" /><point x="78.264" y="179.032" time="889509" /><point x="79.264" y="179.032" time="1019700" /><point x="80.264" y="179.032" time="1059524" /><point x="81.264" y="179.032" time="1179698" /><point x="83.264" y="179.032" time="1219524" /><point x="87.264" y="179.032" time="1469814" /><point x="92.264" y="178.032" time="1583618" /><point x="98.264" y="176.032" time="1689957" /><point x="105.264" y="174.032" time="1861936" /><point x="117.264" y="169.032" time="2099547" /><point x="125.264" y="167.032" time="2219536" /><point x="134.264" y="164.032" time="2382795" /><point x="142.264" y="162.032" time="2502794" /><point x="149.264" y="160.032" time="2614407" /><point x="155.264" y="158.032" time="2774815" /><point x="163.264" y="155.032" time="3024821" /><point x="166.264" y="154.032" time="3144838" /><point x="169.264" y="153.032" time="3265334" /><point x="170.264" y="153.032" time="3505410" /><point x="172.264" y="152.032" time="3599824" /><point x="172.264" y="152.032" time="3609827" /><point x="172.264" y="152.032" time="3738510" /><point x="172.264" y="152.032" time="3778493" /><point x="172.264" y="152.032" time="3858620" /><point x="172.264" y="152.032" time="3888697" /><point x="172.264" y="153.032" time="4029416" /><point x="171.264" y="153.032" time="4240450" /><point x="171.264" y="154.032" time="4321455" /><point x="171.264" y="155.032" time="4585790" /><point x="170.264" y="157.032" time="4685597" /><point x="168.264" y="160.032" time="4865807" /><point x="166.264" y="164.032" time="5025482" /><point x="164.264" y="169.032" time="5145493" /><point x="159.264" y="178.032" time="5385632" /><point x="156.264" y="184.032" time="5505651" /><point x="153.264" y="190.032" time="5658163" /><point x="150.264" y="196.032" time="5786194" /><point x="146.264" y="203.032" time="5899798" /><point x="143.264" y="209.032" time="6065541" /><point x="138.264" y="218.032" time="6303163" /><point x="134.264" y="224.032" time="6427492" /><point x="131.264" y="230.032" time="6579538" /><point x="128.264" y="236.032" time="6740202" /><point x="123.264" y="245.032" time="6944582" /><point x="119.264" y="252.032" time="7066672" /><point x="116.264" y="258.032" time="7226678" /><point x="113.264" y="264.032" time="7326476" /><point x="109.264" y="274.032" time="7576865" /><point x="102.264" y="288.032" time="7796694" /><point x="98.264" y="294.032" time="7966522" /><point x="97.264" y="297.032" time="7976522" /><point x="95.264" y="299.032" time="8139425" /><point x="92.264" y="303.032" time="8260522" /><point x="90.264" y="307.032" time="8419514" /><point x="87.264" y="313.032" time="8660389" /><point x="86.264" y="317.032" time="8786402" /><point x="84.264" y="319.032" time="8938300" /><point x="84.264" y="321.032" time="9037938" /><point x="84.264" y="321.032" time="9047952" /><point x="84.264" y="321.032" time="9157906" /><point x="84.264" y="321.032" time="9317623" /><point x="84.264" y="321.032" time="9507773" /><point x="84.264" y="321.032" time="9527911" /><point x="84.264" y="321.032" time="9707977" /><point x="84.264" y="321.032" time="9787983" /><point x="84.264" y="321.032" time="9817985" /><point x="84.264" y="321.032" time="10018156" /><point x="86.264" y="318.032" time="10218163" /><point x="87.264" y="316.032" time="10338271" /><point x="90.264" y="312.032" time="10507691" /><point x="93.264" y="309.032" time="10659210" /><point x="97.264" y="306.032" time="10769305" /><point x="102.264" y="302.032" time="10941586" /><point x="109.264" y="296.032" time="11071732" /><point x="114.264" y="290.032" time="11308637" /><point x="120.264" y="285.032" time="11418331" /><point x="125.264" y="279.032" time="11578316" /><point x="132.264" y="272.032" time="11698915" /><point x="141.264" y="264.032" time="11938964" /><point x="147.264" y="259.032" time="12068477" /><point x="154.264" y="254.032" time="12228504" /><point x="160.264" y="248.032" time="12343331" /><point x="167.264" y="242.032" time="12459087" /><point x="173.264" y="236.032" time="12589176" /><point x="182.264" y="228.032" time="12859335" /><point x="188.264" y="223.032" time="12979491" /><point x="194.264" y="219.032" time="13115943" /><point x="199.264" y="214.032" time="13259484" /><point x="208.264" y="208.032" time="13500407" /><point x="213.264" y="204.032" time="13580404" /><point x="216.264" y="202.032" time="13620415" /><point x="218.264" y="201.032" time="13780427" /><point x="222.264" y="197.032" time="13940431" /><point x="227.264" y="194.032" time="14070447" /><point x="232.264" y="191.032" time="14150456" /><point x="239.264" y="187.032" time="14427414" /><point x="244.264" y="184.032" time="14529386" /><point x="246.264" y="183.032" time="14529386" /><point x="249.264" y="181.032" time="14699492" /><point x="254.264" y="178.032" time="14821515" /><point x="261.264" y="175.032" time="15064092" /><point x="265.264" y="172.032" time="15225339" /><point x="270.264" y="170.032" time="15339770" /><point x="274.264" y="168.032" time="15500528" /><point x="279.264" y="166.032" time="15620533" /><point x="284.264" y="165.032" time="15730544" /><point x="289.264" y="163.032" time="15900559" /><point x="296.264" y="162.032" time="16140562" /><point x="300.264" y="162.032" time="16260576" /><point x="305.264" y="162.032" time="16381072" /><point x="308.264" y="162.032" time="16540584" /><point x="314.264" y="163.032" time="16780596" /><point x="318.264" y="164.032" time="16904400" /><point x="322.264" y="164.032" time="17066410" /><point x="327.264" y="166.032" time="17176080" /><point x="333.264" y="169.032" time="17420289" /><point x="341.264" y="175.032" time="17701794" /><point x="344.264" y="179.032" time="17861674" /><point x="346.264" y="183.032" time="17981802" /><point x="348.264" y="189.032" time="18112262" /><point x="350.264" y="197.032" time="18341692" /><point x="352.264" y="202.032" time="18499656" /><point x="353.264" y="208.032" time="18570489" /><point x="354.264" y="213.032" time="18782337" /><point x="356.264" y="219.032" time="18899660" /><point x="358.264" y="228.032" time="19149859" /><point x="361.264" y="239.032" time="19422516" /><point x="363.264" y="245.032" time="19503763" /><point x="364.264" y="251.032" time="19669825" /><point x="365.264" y="257.032" time="19819828" /><point x="365.264" y="260.032" time="19839831" /><point x="366.264" y="265.032" time="20059708" /><point x="366.264" y="270.032" time="20179716" /><point x="367.264" y="275.032" time="20339758" /><point x="367.264" y="281.032" time="20439866" /><point x="368.264" y="290.032" time="20699754" /><point x="366.264" y="300.032" time="20920805" /><point x="365.264" y="304.032" time="21147300" /><point x="364.264" y="309.032" time="21259390" /><point x="362.264" y="314.032" time="21383163" /><point x="359.264" y="322.032" time="21619700" /><point x="357.264" y="328.032" time="21779914" /><point x="354.264" y="334.032" time="21869986" /><point x="350.264" y="339.032" time="22059992" /><point x="345.264" y="346.032" time="22259909" /><point x="341.264" y="350.032" time="22420042" /><point x="334.264" y="358.032" time="22699999" /><point x="331.264" y="362.032" time="22819729" /><point x="327.264" y="365.032" time="22940747" /><point x="324.264" y="368.032" time="23109999" /><point x="319.264" y="372.032" time="23274486" /><point x="316.264" y="375.032" time="23468975" /><point x="312.264" y="378.032" time="23629476" /><point x="309.264" y="380.032" time="23744535" /><point x="303.264" y="382.032" time="23978468" /><point x="300.264" y="384.032" time="24099112" /><point x="295.264" y="384.032" time="24179118" /><point x="293.264" y="384.032" time="24269130" /><point x="290.264" y="384.032" time="24349136" /><point x="285.264" y="383.032" time="24539138" /><point x="280.264" y="382.032" time="24629147" /><point x="274.264" y="380.032" time="24899657" /><point x="270.264" y="379.032" time="25059660" /><point x="266.264" y="377.032" time="25179655" /><point x="262.264" y="374.032" time="25339275" /><point x="257.264" y="370.032" time="25539190" /><point x="254.264" y="366.032" time="25699335" /><point x="249.264" y="357.032" time="25979566" /><point x="248.264" y="352.032" time="26099550" /><point x="248.264" y="347.032" time="26199833" /><point x="249.264" y="342.032" time="26389832" /><point x="253.264" y="335.032" time="26619703" /><point x="256.264" y="331.032" time="26739774" /><point x="259.264" y="328.032" time="26899868" /><point x="262.264" y="325.032" time="27009912" /><point x="267.264" y="322.032" time="27269936" /><point x="271.264" y="321.032" time="27379923" /><point x="276.264" y="320.032" time="27545146" /><point x="281.264" y="319.032" time="27708544" /><point x="288.264" y="319.032" time="27768662" /><point x="291.264" y="318.032" time="27778478" /><point x="294.264" y="318.032" time="27950457" /><point x="303.264" y="320.032" time="28186194" /><point x="309.264" y="321.032" time="28347078" /><point x="315.264" y="323.032" time="28420154" /><point x="322.264" y="326.032" time="28620161" /><point x="332.264" y="331.032" time="28820193" /><point x="338.264" y="334.032" time="28980182" /><point x="350.264" y="339.032" time="29260199" /><point x="355.264" y="343.032" time="29380206" /><point x="360.264" y="346.032" time="29540379" /><point x="365.264" y="350.032" time="29620222" /><point x="367.264" y="352.032" time="29660272" /><point x="372.264" y="356.032" time="29910242" /><point x="378.264" y="361.032" time="30020247" /><point x="382.264" y="365.032" time="30179619" /><point x="386.264" y="369.032" time="30300861" /><point x="391.264" y="374.032" time="30539564" /><point x="394.264" y="376.032" time="30659620" /><point x="396.264" y="378.032" time="30750136" /><point x="399.264" y="380.032" time="30943894" /><point x="401.264" y="380.032" time="31039482" /><point x="403.264" y="379.032" time="31242456" /><point x="403.264" y="379.032" time="31261780" /><point x="403.264" y="379.032" time="31332378" /></stroke></sketch>