<?xml version="1.0" encoding="utf-8"?><sketch label="me"><stroke><point x="443.092" y="134.088" time="0" /><point x="444.092" y="133.088" time="0" /><point x="445.092" y="133.088" time="0" /><point x="445.092" y="134.088" time="155927" /><point x="445.092" y="135.088" time="312551" /><point x="445.092" y="136.088" time="312551" /><point x="445.092" y="138.088" time="485287" /><point x="444.092" y="140.088" time="521010" /><point x="443.092" y="143.088" time="521010" /><point x="441.092" y="145.088" time="677887" /><point x="439.092" y="149.088" time="677887" /><point x="437.092" y="153.088" time="677887" /><point x="434.092" y="157.088" time="833811" /><point x="431.092" y="162.088" time="833811" /><point x="427.092" y="168.088" time="990589" /><point x="423.092" y="174.088" time="990589" /><point x="419.092" y="181.088" time="1146510" /><point x="414.092" y="189.088" time="1146510" /><point x="409.092" y="197.088" time="1303049" /><point x="403.092" y="205.088" time="1303049" /><point x="397.092" y="214.088" time="1303049" /><point x="391.092" y="223.088" time="1458789" /><point x="384.092" y="233.088" time="1458789" /><point x="377.092" y="243.088" time="1615521" /><point x="370.092" y="253.088" time="1615521" /><point x="362.092" y="264.088" time="1771798" /><point x="354.092" y="275.088" time="1771798" /><point x="345.092" y="287.088" time="1927227" /><point x="337.092" y="299.088" time="1927227" /><point x="327.092" y="312.088" time="1927227" /><point x="318.092" y="325.088" time="2083808" /><point x="308.092" y="338.088" time="2083808" /><point x="298.092" y="350.088" time="2240544" /><point x="287.092" y="363.088" time="2240544" /><point x="277.092" y="374.088" time="2395948" /><point x="267.092" y="386.088" time="2395948" /><point x="258.092" y="397.088" time="2552539" /><point x="249.092" y="408.088" time="2552539" /><point x="240.092" y="418.088" time="2552539" /><point x="231.092" y="428.088" time="2709338" /><point x="223.092" y="437.088" time="2709338" /><point x="216.092" y="446.088" time="2865539" /><point x="209.092" y="454.088" time="2865539" /><point x="203.092" y="461.088" time="3021849" /><point x="203.092" y="461.088" time="3021849" /></stroke><stroke><point x="264.092" y="238.088" time="0" /><point x="265.092" y="238.088" time="155912" /><point x="266.092" y="238.088" time="312699" /><point x="268.092" y="238.088" time="312699" /><point x="270.092" y="239.088" time="468125" /><point x="272.092" y="240.088" time="468125" /><point x="275.092" y="242.088" time="468125" /><point x="278.092" y="244.088" time="624658" /><point x="282.092" y="246.088" time="624658" /><point x="286.092" y="249.088" time="781415" /><point x="290.092" y="253.088" time="781415" /><point x="295.092" y="257.088" time="937634" /><point x="300.092" y="262.088" time="937634" /><point x="306.092" y="267.088" time="937634" /><point x="312.092" y="273.088" time="1093413" /><point x="318.092" y="279.088" time="1093413" /><point x="324.092" y="286.088" time="1249575" /><point x="331.092" y="292.088" time="1249575" /><point x="338.092" y="299.088" time="1405903" /><point x="345.092" y="305.088" time="1405903" /><point x="352.092" y="312.088" time="1405903" /><point x="359.092" y="319.088" time="1562207" /><point x="365.092" y="325.088" time="1562207" /><point x="372.092" y="331.088" time="1718698" /><point x="378.092" y="338.088" time="1718698" /><point x="384.092" y="344.088" time="1874655" /><point x="389.092" y="349.088" time="1874655" /><point x="395.092" y="355.088" time="1874655" /><point x="395.092" y="355.088" time="2030899" /></stroke></sketch>