<?xml version="1.0" encoding="utf-8"?><sketch label="tsu"><stroke><point x="156.192" y="220.688" time="0" /><point x="156.192" y="221.688" time="130085" /><point x="156.192" y="221.688" time="140088" /><point x="156.192" y="221.688" time="290743" /><point x="156.192" y="222.688" time="300739" /><point x="156.192" y="222.688" time="440455" /><point x="156.192" y="222.688" time="450458" /><point x="156.192" y="222.688" time="663407" /><point x="157.192" y="222.688" time="693402" /><point x="158.192" y="221.688" time="803411" /><point x="158.192" y="221.688" time="823410" /><point x="160.192" y="220.688" time="943544" /><point x="161.192" y="219.688" time="953528" /><point x="163.192" y="217.688" time="1108642" /><point x="168.192" y="214.688" time="1298647" /><point x="174.192" y="209.688" time="1448661" /><point x="181.192" y="205.688" time="1608677" /><point x="189.192" y="200.688" time="1798675" /><point x="198.192" y="196.688" time="1868687" /><point x="208.192" y="191.688" time="2053791" /><point x="220.192" y="185.688" time="2168888" /><point x="226.192" y="182.688" time="2178897" /><point x="233.192" y="179.688" time="2365354" /><point x="271.192" y="166.688" time="2759088" /><point x="288.192" y="161.688" time="2915691" /><point x="323.192" y="155.688" time="3199960" /><point x="339.192" y="155.688" time="3349968" /><point x="354.192" y="156.688" time="3489979" /><point x="367.192" y="159.688" time="3679990" /><point x="378.192" y="165.688" time="3739987" /><point x="383.192" y="168.688" time="3749996" /><point x="386.192" y="172.688" time="3935099" /><point x="392.192" y="182.688" time="4080852" /><point x="396.192" y="198.688" time="4310162" /><point x="397.192" y="211.688" time="4460342" /><point x="395.192" y="224.688" time="4622880" /><point x="393.192" y="238.688" time="4800303" /><point x="384.192" y="261.688" time="5059108" /><point x="378.192" y="270.688" time="5209192" /><point x="371.192" y="277.688" time="5399177" /><point x="364.192" y="283.688" time="5549191" /><point x="357.192" y="288.688" time="5609194" /><point x="351.192" y="292.688" time="5779219" /><point x="346.192" y="297.688" time="5909209" /><point x="341.192" y="304.688" time="6189674" /><point x="341.192" y="304.688" time="6329576" /></stroke></sketch>